{
  "red": {
    "faint": "#f4aca4",
    "light": "#E36B6B",
    "solid": "#D92E42",
    "dark": "#98222A"
  },
  "orange": {
    "faint": "#ffb97c",
    "light": "#F88B55",
    "solid": "#E87341",
    "dark": "#B34822"
  },
  "yellow": {
    "faint": "#ffe47c",
    "light": "#FBCD58",
    "solid": "#ECB32C",
    "dark": "#B27821"
  },
  "green": {
    "faint": "#a6dba7",
    "light": "#97C4AE",
    "solid": "#6FAE91",
    "dark": "#4A7C59"
  },
  "teal": {
    "faint": "#b2ffef",
    "light": "#81FBD7",
    "solid": "#41E8CC",
    "dark": "#22B3A9"
  },
  "blue": {
    "faint": "#b7ceff",
    "light": "#80B8EF",
    "solid": "#4d89e3",
    "dark": "#3E517A"
  },
  "pink": {
    "faint": "#ffa5c4",
    "light": "#ff66ad",
    "solid": "#f714b3",
    "dark": "#d10073"
  },
  "magenta": {
    "faint": "#f196ff",
    "light": "#DE35EA",
    "solid": "#BB16CD",
    "dark": "#8A1997"
  },
  "purple": {
    "faint": "#c99ef7",
    "light": "#8A68E7",
    "solid": "#6540E7",
    "dark": "#4122B3"
  }
}
